cr_pulse_interpolator/__init__.py
cr_pulse_interpolator/interpolation_fourier.py
cr_pulse_interpolator/signal_interpolation_fourier.py
cr_pulse_interpolator-1.1.1.dist-info/licenses/LICENSE
cr_pulse_interpolator-1.1.1.dist-info/METADATA
cr_pulse_interpolator-1.1.1.dist-info/WHEEL
cr_pulse_interpolator-1.1.1.dist-info/top_level.txt
cr_pulse_interpolator-1.1.1.dist-info/RECORD
