Metadata-Version: 2.4
Name: cr_pulse_interpolator
Version: 1.1.1
Summary: Full waveform interpolation for air shower simulations
Author-email: Arthur Corstanje <a.corstanje@astro.ru.nl>
Project-URL: Homepage, https://github.com/nu-radio/cr-pulse-interpolator
Project-URL: Issues, https://github.com/nu-radio/cr-pulse-interpolator/issues
Classifier: Programming Language :: Python :: 3
Classifier: License :: OSI Approved :: GNU General Public License v3 (GPLv3)
Classifier: Operating System :: OS Independent
Requires-Python: >=3.7
License-File: LICENSE
Requires-Dist: numpy>=1.20
Requires-Dist: scipy>=1.7
Provides-Extra: demo
Requires-Dist: h5py; extra == "demo"
Requires-Dist: matplotlib; extra == "demo"
Dynamic: license-file
